{"userProfile":{"firstName":"Benedict","lastName":"Abrasaldo Jr.","dateOfBirth":"9/22/2006 12:00:00 AM","primaryEmail":"benedict.abrasaldo@outlook.com","gender":"Man","genderPronounPreference":"He/Him/His","puid":"00037FFF8BB876B4","oid":"00000000-0000-0000-3516-717304bef1c1","isPrivate":false,"isTextOptIn":false,"isPrivacyAgreed":true,"deleted":false,"modifiedBy":"benedict.abrasaldo@outlook.com","createdBy":"benedict.abrasaldo@outlook.com","dateCreated":"2026-06-04T16:53:21.8812311","dateModified":"2026-06-04T16:57:10.1576714","addresses":[{"addressType":"Primary","stateOrProvince":"Metro Manila","countryOrRegion":"Philippines","createdBy":"benedict.abrasaldo@outlook.com","modifiedBy":"benedict.abrasaldo@outlook.com","dateCreated":"2026-06-04T16:53:25.0345339","dateModified":"2026-06-04T16:57:05.2764085","deleted":false}],"phoneInfo":[{"phoneType":"Mobile","isVerified":false,"dateCreated":"2026-06-04T16:53:25.0346516","dateModified":"2026-06-04T16:57:05.2764215","createdBy":"benedict.abrasaldo@outlook.com","modifiedBy":"benedict.abrasaldo@outlook.com"}],"socialNetworks":[],"languages":[],"programmingLanguages":[{"programmingLanguage":"Java"},{"programmingLanguage":"PHP"},{"programmingLanguage":"Python"}],"functionalRoles":[],"azureBenefitRequestForms":[],"azureBenefits":[]},"studentAmbassadorProgram":{"events":[],"activities":[],"applications":[{"formType":"Application","formStatus":"Under Review","dateModified":"2026-06-04T16:57:04.7708336","dateCreated":"2026-06-04T16:53:21.8812311","modifiedBy":"benedict.abrasaldo@outlook.com","createdBy":"benedict.abrasaldo@outlook.com","deleted":false,"dateSubmitted":"2026-06-04T16:57:04.7708337","answers":[{"question":"Which of the following technologies interest you?","optionText":"Internet of Things"},{"question":"What is the User Name for your Microsoft Learn account? All registered members are required to have a Microsoft Learn account. If you do not have a Learn account, create one now. https://aka.ms/LearnAccountSettings.","answer":"Benedict"}]}],"nominations":[],"school":{"schoolName":"Olivarez College Computer","countryOrRegion":"Philippines","schoolDegreeProgram":"Other","schoolDegreeLevel":"Bachelor","expectedGraduationDate":"2028-05-28T16:00:00"},"benefits":[],"strengths":[],"testimonials":[],"visualStudioBenefitRequests":[],"visualStudioBenefitDetails":[]},"isSuccess":true}